hdl_shared/HDL/source/nihdlregister.vhd
hdl_shared/HDL/testbench/tb_nihdlregister.vhd
hdl_shared/LabVIEW/NiFpga_Dynamic_ReadU32.vi
hdl_shared/__init__.py
hdl_shared-0.0.1.dist-info/METADATA
hdl_shared-0.0.1.dist-info/WHEEL
hdl_shared-0.0.1.dist-info/RECORD
